visualization/__init__.py
visualization/plot.py
visualization/plot_utils.py
visualization/edf_saving/__init__.py
visualization/edf_saving/anonymizer.py
visualization/edf_saving/saveEdf_info.py
visualization/edf_saving/saveEdf_options.py
visualization/filtering/__init__.py
visualization/filtering/filter_info.py
visualization/filtering/filter_options.py
visualization/image_saving/__init__.py
visualization/image_saving/saveImg_info.py
visualization/image_saving/saveImg_options.py
visualization/image_saving/saveTopoplot_options.py
visualization/models/__init__.py
visualization/models/basemodel.py
visualization/models/sklearnchannelmodels.py
visualization/models/sklearnmodels.py
visualization/predictions/__init__.py
visualization/predictions/prediction_info.py
visualization/predictions/prediction_options.py
visualization/preprocessing/__init__.py
visualization/preprocessing/dsp.py
visualization/preprocessing/edf_loader.py
visualization/preprocessing/eeg_info.py
visualization/signal_loading/__init__.py
visualization/signal_loading/channel_info.py
visualization/signal_loading/channel_options.py
visualization/signal_loading/color_options.py
visualization/signal_loading/organize_channels.py
visualization/signal_stats/__init__.py
visualization/signal_stats/signalStats_info.py
visualization/signal_stats/signalStats_options.py
visualization/spectrogram_window/__init__.py
visualization/spectrogram_window/spec_info.py
visualization/spectrogram_window/spec_options.py
visualization/ui_files/__init__.py
visualization/ui_files/anon_ui.py
visualization/ui_files/gui_stylesheet.css
visualization/ui_files/saveEdfOps.py
visualization/ui_files/saveImg.py
EPViz-0.0.0.dist-info/LICENSE
EPViz-0.0.0.dist-info/METADATA
EPViz-0.0.0.dist-info/WHEEL
EPViz-0.0.0.dist-info/entry_points.txt
EPViz-0.0.0.dist-info/top_level.txt
EPViz-0.0.0.dist-info/RECORD
