Metadata-Version: 2.1
Name: EPViz
Version: 0.0.0
Summary: An open source EEG Visualization software
Home-page: https://github.com/jcraley/epviz
License: UNKNOWN
Project-URL: Bug Tracker, https://github.com/jcraley/epviz/issues
Project-URL: Documentation, https://engineering.jhu.edu/nsa/links/epviz/
Platform: UNKNOWN
License-File: LICENSE
